qctrlmkdocstheme/404.html
qctrlmkdocstheme/__init__.py
qctrlmkdocstheme/apple-touch-icon.png
qctrlmkdocstheme/assets/css/style.css
qctrlmkdocstheme/assets/css/style.css.map
qctrlmkdocstheme/assets/img/bloch-sphere-dark.svg
qctrlmkdocstheme/assets/img/bloch-sphere.svg
qctrlmkdocstheme/assets/img/image.jpg
qctrlmkdocstheme/assets/img/logo-white.svg
qctrlmkdocstheme/assets/img/logo.svg
qctrlmkdocstheme/assets/js/mathjax-config.js
qctrlmkdocstheme/assets/js/script.js
qctrlmkdocstheme/base.html
qctrlmkdocstheme/favicon.ico
qctrlmkdocstheme/includes/breadcrumb.html
qctrlmkdocstheme/includes/content.html
qctrlmkdocstheme/includes/copyright.html
qctrlmkdocstheme/includes/nav.html
qctrlmkdocstheme/includes/navbar-brand.html
qctrlmkdocstheme/includes/pagination.html
qctrlmkdocstheme/includes/source.html
qctrlmkdocstheme/includes/toc-items.html
qctrlmkdocstheme/includes/toc.html
qctrlmkdocstheme/main.html
qctrlmkdocstheme/mkdocs_theme.yml
qctrl_mkdocs_theme-1.2.2.dist-info/METADATA
qctrl_mkdocs_theme-1.2.2.dist-info/WHEEL
qctrl_mkdocs_theme-1.2.2.dist-info/entry_points.txt
qctrl_mkdocs_theme-1.2.2.dist-info/RECORD
